{
    "background": "bright",
    "classes": [
        "E.coli"
    ],
    "colonies_number": 4,
    "labels": [
        {
            "class": "E.coli",
            "height": 210,
            "id": 1,
            "width": 210,
            "x": 2233,
            "y": 672
        },
        {
            "class": "E.coli",
            "height": 231,
            "id": 2,
            "width": 231,
            "x": 2492,
            "y": 1080
        },
        {
            "class": "E.coli",
            "height": 210,
            "id": 3,
            "width": 210,
            "x": 2039,
            "y": 1761
        },
        {
            "class": "E.coli",
            "height": 254,
            "id": 4,
            "width": 254,
            "x": 1797,
            "y": 2830
        }
    ],
    "sample_id": 1290
}