{
    "background": "lower-resolution",
    "classes": [
        "S.aureus"
    ],
    "colonies_number": 5,
    "labels": [
        {
            "class": "S.aureus",
            "height": 38,
            "id": 1,
            "width": 38,
            "x": 1474,
            "y": 261
        },
        {
            "class": "S.aureus",
            "height": 51,
            "id": 2,
            "width": 51,
            "x": 1511,
            "y": 763
        },
        {
            "class": "S.aureus",
            "height": 38,
            "id": 3,
            "width": 38,
            "x": 691,
            "y": 1192
        },
        {
            "class": "S.aureus",
            "height": 42,
            "id": 4,
            "width": 42,
            "x": 212,
            "y": 1209
        },
        {
            "class": "S.aureus",
            "height": 38,
            "id": 5,
            "width": 38,
            "x": 368,
            "y": 781
        }
    ],
    "sample_id": 14306
}