{
    "background": "lower-resolution",
    "classes": [
        "P.aeruginosa",
        "S.aureus"
    ],
    "colonies_number": 2,
    "labels": [
        {
            "class": "S.aureus",
            "height": 38,
            "id": 1,
            "width": 38,
            "x": 1258,
            "y": 1249
        },
        {
            "class": "P.aeruginosa",
            "height": 250,
            "id": 2,
            "width": 250,
            "x": 585,
            "y": 491
        }
    ],
    "sample_id": 15344
}