{
    "background": "lower-resolution",
    "classes": [
        "E.coli"
    ],
    "colonies_number": 4,
    "labels": [
        {
            "class": "E.coli",
            "height": 227,
            "id": 1,
            "width": 227,
            "x": 472,
            "y": 1349
        },
        {
            "class": "E.coli",
            "height": 206,
            "id": 2,
            "width": 206,
            "x": 1183,
            "y": 1141
        },
        {
            "class": "E.coli",
            "height": 250,
            "id": 3,
            "width": 250,
            "x": 825,
            "y": 790
        },
        {
            "class": "E.coli",
            "height": 227,
            "id": 4,
            "width": 227,
            "x": 992,
            "y": 225
        }
    ],
    "sample_id": 15906
}