{
    "background": "lower-resolution",
    "classes": [
        "E.coli",
        "P.aeruginosa"
    ],
    "colonies_number": 4,
    "labels": [
        {
            "class": "P.aeruginosa",
            "height": 128,
            "id": 1,
            "width": 128,
            "x": 801,
            "y": 681
        },
        {
            "class": "P.aeruginosa",
            "height": 117,
            "id": 2,
            "width": 117,
            "x": 1349,
            "y": 567
        },
        {
            "class": "Contamination",
            "height": 24,
            "id": 3,
            "width": 24,
            "x": 1134,
            "y": 504
        },
        {
            "class": "P.aeruginosa",
            "height": 155,
            "id": 4,
            "width": 155,
            "x": 1145,
            "y": 409
        },
        {
            "class": "E.coli",
            "height": 128,
            "id": 5,
            "width": 128,
            "x": 1456,
            "y": 326
        }
    ],
    "sample_id": 16066
}