{
    "background": "dark",
    "classes": [
        "C.albicans"
    ],
    "colonies_number": 7,
    "labels": [
        {
            "class": "C.albicans",
            "height": 45,
            "id": 1,
            "width": 45,
            "x": 2975,
            "y": 3027
        },
        {
            "class": "C.albicans",
            "height": 45,
            "id": 2,
            "width": 45,
            "x": 3244,
            "y": 2548
        },
        {
            "class": "C.albicans",
            "height": 45,
            "id": 3,
            "width": 45,
            "x": 3071,
            "y": 2004
        },
        {
            "class": "C.albicans",
            "height": 45,
            "id": 4,
            "width": 45,
            "x": 2301,
            "y": 2025
        },
        {
            "class": "C.albicans",
            "height": 45,
            "id": 5,
            "width": 45,
            "x": 2510,
            "y": 1040
        },
        {
            "class": "C.albicans",
            "height": 45,
            "id": 6,
            "width": 45,
            "x": 1452,
            "y": 823
        },
        {
            "class": "C.albicans",
            "height": 45,
            "id": 7,
            "width": 45,
            "x": 1387,
            "y": 848
        }
    ],
    "sample_id": 2924
}