{
    "background": "dark",
    "classes": [
        "B.subtilis"
    ],
    "colonies_number": 31,
    "labels": [
        {
            "class": "B.subtilis",
            "height": 279,
            "id": 1,
            "width": 279,
            "x": 288,
            "y": 1992
        },
        {
            "class": "B.subtilis",
            "height": 231,
            "id": 2,
            "width": 231,
            "x": 310,
            "y": 2257
        },
        {
            "class": "B.subtilis",
            "height": 258,
            "id": 3,
            "width": 231,
            "x": 993,
            "y": 2507
        },
        {
            "class": "B.subtilis",
            "height": 231,
            "id": 4,
            "width": 231,
            "x": 1209,
            "y": 2520
        },
        {
            "class": "B.subtilis",
            "height": 372,
            "id": 5,
            "width": 372,
            "x": 1303,
            "y": 1421
        },
        {
            "class": "B.subtilis",
            "height": 409,
            "id": 6,
            "width": 409,
            "x": 1100,
            "y": 1656
        },
        {
            "class": "B.subtilis",
            "height": 210,
            "id": 7,
            "width": 218,
            "x": 1243,
            "y": 620
        },
        {
            "class": "B.subtilis",
            "height": 279,
            "id": 8,
            "width": 313,
            "x": 1163,
            "y": 824
        },
        {
            "class": "B.subtilis",
            "height": 338,
            "id": 9,
            "width": 338,
            "x": 1762,
            "y": 762
        },
        {
            "class": "B.subtilis",
            "height": 307,
            "id": 10,
            "width": 307,
            "x": 2465,
            "y": 873
        },
        {
            "class": "B.subtilis",
            "height": 254,
            "id": 11,
            "width": 254,
            "x": 2842,
            "y": 1570
        },
        {
            "class": "B.subtilis",
            "height": 279,
            "id": 12,
            "width": 279,
            "x": 2295,
            "y": 1513
        },
        {
            "class": "B.subtilis",
            "height": 254,
            "id": 13,
            "width": 254,
            "x": 2414,
            "y": 1682
        },
        {
            "class": "B.subtilis",
            "height": 210,
            "id": 14,
            "width": 258,
            "x": 1694,
            "y": 2012
        },
        {
            "class": "B.subtilis",
            "height": 254,
            "id": 15,
            "width": 308,
            "x": 1741,
            "y": 1826
        },
        {
            "class": "B.subtilis",
            "height": 208,
            "id": 16,
            "width": 233,
            "x": 2104,
            "y": 2358
        },
        {
            "class": "B.subtilis",
            "height": 254,
            "id": 17,
            "width": 254,
            "x": 2205,
            "y": 2504
        },
        {
            "class": "B.subtilis",
            "height": 190,
            "id": 18,
            "width": 190,
            "x": 1952,
            "y": 2606
        },
        {
            "class": "B.subtilis",
            "height": 210,
            "id": 19,
            "width": 210,
            "x": 2094,
            "y": 2718
        },
        {
            "class": "B.subtilis",
            "height": 263,
            "id": 20,
            "width": 225,
            "x": 3172,
            "y": 2158
        },
        {
            "class": "B.subtilis",
            "height": 254,
            "id": 21,
            "width": 254,
            "x": 2655,
            "y": 2848
        },
        {
            "class": "B.subtilis",
            "height": 231,
            "id": 22,
            "width": 248,
            "x": 2846,
            "y": 2677
        },
        {
            "class": "B.subtilis",
            "height": 130,
            "id": 23,
            "width": 130,
            "x": 2998,
            "y": 2925
        },
        {
            "class": "B.subtilis",
            "height": 143,
            "id": 24,
            "width": 143,
            "x": 3065,
            "y": 2820
        },
        {
            "class": "B.subtilis",
            "height": 143,
            "id": 25,
            "width": 143,
            "x": 2901,
            "y": 3026
        },
        {
            "class": "B.subtilis",
            "height": 173,
            "id": 26,
            "width": 173,
            "x": 2763,
            "y": 3129
        },
        {
            "class": "B.subtilis",
            "height": 231,
            "id": 27,
            "width": 240,
            "x": 1901,
            "y": 3467
        },
        {
            "class": "B.subtilis",
            "height": 231,
            "id": 28,
            "width": 231,
            "x": 1304,
            "y": 2778
        },
        {
            "class": "B.subtilis",
            "height": 173,
            "id": 29,
            "width": 173,
            "x": 1747,
            "y": 2662
        },
        {
            "class": "B.subtilis",
            "height": 231,
            "id": 30,
            "width": 231,
            "x": 1628,
            "y": 2722
        },
        {
            "class": "B.subtilis",
            "height": 254,
            "id": 31,
            "width": 254,
            "x": 1795,
            "y": 2868
        }
    ],
    "sample_id": 4720
}