{
    "background": "bright",
    "classes": [
        "S.aureus"
    ],
    "colonies_number": 3,
    "labels": [
        {
            "class": "S.aureus",
            "height": 50,
            "id": 1,
            "width": 50,
            "x": 679,
            "y": 1275
        },
        {
            "class": "S.aureus",
            "height": 50,
            "id": 2,
            "width": 50,
            "x": 1887,
            "y": 1260
        },
        {
            "class": "S.aureus",
            "height": 50,
            "id": 3,
            "width": 50,
            "x": 2289,
            "y": 1986
        }
    ],
    "sample_id": 495
}