{
    "background": "bright",
    "classes": [
        "E.coli"
    ],
    "colonies_number": 9,
    "labels": [
        {
            "class": "E.coli",
            "height": 210,
            "id": 1,
            "width": 210,
            "x": 1582,
            "y": 449
        },
        {
            "class": "E.coli",
            "height": 73,
            "id": 2,
            "width": 73,
            "x": 2226,
            "y": 458
        },
        {
            "class": "E.coli",
            "height": 97,
            "id": 3,
            "width": 97,
            "x": 463,
            "y": 1309
        },
        {
            "class": "E.coli",
            "height": 173,
            "id": 4,
            "width": 173,
            "x": 267,
            "y": 1702
        },
        {
            "class": "E.coli",
            "height": 157,
            "id": 5,
            "width": 157,
            "x": 1276,
            "y": 3435
        },
        {
            "class": "E.coli",
            "height": 190,
            "id": 6,
            "width": 190,
            "x": 1690,
            "y": 3531
        },
        {
            "class": "E.coli",
            "height": 130,
            "id": 7,
            "width": 130,
            "x": 2702,
            "y": 3353
        },
        {
            "class": "E.coli",
            "height": 190,
            "id": 8,
            "width": 190,
            "x": 2844,
            "y": 3138
        },
        {
            "class": "E.coli",
            "height": 173,
            "id": 9,
            "width": 173,
            "x": 3313,
            "y": 2616
        }
    ],
    "sample_id": 560
}