{
    "background": "dark",
    "classes": [
        "P.aeruginosa"
    ],
    "colonies_number": 8,
    "labels": [
        {
            "class": "P.aeruginosa",
            "height": 276,
            "id": 1,
            "width": 290,
            "x": 1063,
            "y": 1727
        },
        {
            "class": "P.aeruginosa",
            "height": 304,
            "id": 2,
            "width": 304,
            "x": 860,
            "y": 1628
        },
        {
            "class": "P.aeruginosa",
            "height": 276,
            "id": 3,
            "width": 276,
            "x": 1179,
            "y": 1920
        },
        {
            "class": "P.aeruginosa",
            "height": 251,
            "id": 4,
            "width": 262,
            "x": 1659,
            "y": 1462
        },
        {
            "class": "P.aeruginosa",
            "height": 141,
            "id": 5,
            "width": 141,
            "x": 2535,
            "y": 1697
        },
        {
            "class": "P.aeruginosa",
            "height": 88,
            "id": 6,
            "width": 88,
            "x": 2728,
            "y": 2099
        },
        {
            "class": "P.aeruginosa",
            "height": 141,
            "id": 7,
            "width": 141,
            "x": 2469,
            "y": 2721
        },
        {
            "class": "P.aeruginosa",
            "height": 117,
            "id": 8,
            "width": 117,
            "x": 2316,
            "y": 3147
        }
    ],
    "sample_id": 5637
}