{
    "background": "dark",
    "classes": [
        "S.aureus"
    ],
    "colonies_number": 3,
    "labels": [
        {
            "class": "S.aureus",
            "height": 57,
            "id": 1,
            "width": 57,
            "x": 1584,
            "y": 2461
        },
        {
            "class": "S.aureus",
            "height": 57,
            "id": 2,
            "width": 57,
            "x": 1853,
            "y": 2207
        },
        {
            "class": "S.aureus",
            "height": 57,
            "id": 3,
            "width": 57,
            "x": 1266,
            "y": 1057
        }
    ],
    "sample_id": 6353
}