{
    "background": "dark",
    "classes": [
        "P.aeruginosa"
    ],
    "colonies_number": 11,
    "labels": [
        {
            "class": "P.aeruginosa",
            "height": 338,
            "id": 1,
            "width": 410,
            "x": 1675,
            "y": 3084
        },
        {
            "class": "P.aeruginosa",
            "height": 231,
            "id": 2,
            "width": 382,
            "x": 1662,
            "y": 2900
        },
        {
            "class": "P.aeruginosa",
            "height": 338,
            "id": 3,
            "width": 338,
            "x": 2403,
            "y": 2992
        },
        {
            "class": "P.aeruginosa",
            "height": 231,
            "id": 4,
            "width": 231,
            "x": 2756,
            "y": 2679
        },
        {
            "class": "P.aeruginosa",
            "height": 338,
            "id": 5,
            "width": 338,
            "x": 2640,
            "y": 2496
        },
        {
            "class": "P.aeruginosa",
            "height": 118,
            "id": 6,
            "width": 118,
            "x": 1121,
            "y": 2862
        },
        {
            "class": "P.aeruginosa",
            "height": 157,
            "id": 7,
            "width": 157,
            "x": 1033,
            "y": 2807
        },
        {
            "class": "P.aeruginosa",
            "height": 210,
            "id": 8,
            "width": 210,
            "x": 988,
            "y": 1786
        },
        {
            "class": "P.aeruginosa",
            "height": 173,
            "id": 9,
            "width": 173,
            "x": 761,
            "y": 1412
        },
        {
            "class": "P.aeruginosa",
            "height": 210,
            "id": 10,
            "width": 210,
            "x": 1042,
            "y": 1220
        },
        {
            "class": "P.aeruginosa",
            "height": 157,
            "id": 11,
            "width": 157,
            "x": 1253,
            "y": 843
        }
    ],
    "sample_id": 7121
}