{
    "background": "dark",
    "classes": [
        "C.albicans"
    ],
    "colonies_number": 10,
    "labels": [
        {
            "class": "C.albicans",
            "height": 45,
            "id": 1,
            "width": 45,
            "x": 1516,
            "y": 3131
        },
        {
            "class": "C.albicans",
            "height": 45,
            "id": 2,
            "width": 45,
            "x": 1819,
            "y": 2873
        },
        {
            "class": "C.albicans",
            "height": 45,
            "id": 3,
            "width": 45,
            "x": 563,
            "y": 2263
        },
        {
            "class": "C.albicans",
            "height": 45,
            "id": 4,
            "width": 45,
            "x": 411,
            "y": 1625
        },
        {
            "class": "C.albicans",
            "height": 45,
            "id": 5,
            "width": 45,
            "x": 1211,
            "y": 1633
        },
        {
            "class": "C.albicans",
            "height": 45,
            "id": 6,
            "width": 45,
            "x": 2701,
            "y": 2067
        },
        {
            "class": "C.albicans",
            "height": 45,
            "id": 7,
            "width": 45,
            "x": 3319,
            "y": 1990
        },
        {
            "class": "C.albicans",
            "height": 45,
            "id": 8,
            "width": 45,
            "x": 2272,
            "y": 1091
        },
        {
            "class": "C.albicans",
            "height": 45,
            "id": 9,
            "width": 45,
            "x": 1578,
            "y": 718
        },
        {
            "class": "C.albicans",
            "height": 45,
            "id": 10,
            "width": 45,
            "x": 563,
            "y": 1367
        }
    ],
    "sample_id": 7340
}